<?xml version='1.0' encoding='UTF-8'?>
<AUTOMATICALLY_GENERATED_XML>
    <backgroundcolor>#7D79D6</backgroundcolor>
    <height/>
    <width>230</width>
    <hsizepolicy>Expanding</hsizepolicy>
    <vsizepolicy>Expanding</vsizepolicy>
    <margin>2</margin>
    <spacing>0</spacing>
    <frameshape>NoFrame</frameshape>
    <frameshadow>Plain</frameshadow>
    <layout>VBox</layout>
    <headerdescription>
        <global>
            <backgroundcolor>#FFFFFF</backgroundcolor>
            <height/>
            <width/>
            <hsizepolicy>Expanding</hsizepolicy>
            <vsizepolicy>Preferred</vsizepolicy>
            <margin>4</margin>
            <spacing>4</spacing>
            <frameshape>StyledPanel</frameshape>
            <frameshadow>Raised</frameshadow>
            <layout>VBox</layout>
        </global>
        <photo>
            <name>staff_photo</name>
            <pixmap>/usr/share/ntpv_backoffice/apps/48x48/personal.png</pixmap>
            <backgroundcolor>#23ab11</backgroundcolor>
            <height>50</height>
            <width>50</width>
            <hsizepolicy>Maximum</hsizepolicy>
            <vsizepolicy>Maximum</vsizepolicy>
        </photo>
        <labels>
            <label>
                <name>staff_identity</name>
                <text>System User</text>
                <backgroundcolor>#44f0a9</backgroundcolor>
                <halign>Left</halign>
                <valign>Center</valign>
                <hsizepolicy>Expanding</hsizepolicy>
                <vsizepolicy>Maximum</vsizepolicy>
                <fontfamily>SansSerif</fontfamily>
                <fontsize>14</fontsize>
                <bold>true</bold>
            </label>
            <label>
                <name>order_description</name>
                <text/>
                <backgroundcolor>#44f0a9</backgroundcolor>
                <halign>Left</halign>
                <valign>Center</valign>
                <hsizepolicy>Expanding</hsizepolicy>
                <vsizepolicy>Maximum</vsizepolicy>
                <fontfamily>SansSerif</fontfamily>
                <fontsize>10</fontsize>
                <bold>false</bold>
            </label>
        </labels>
    </headerdescription>
    <tabledescription>
        <global>
            <backgroundcolor>#FFFFFF</backgroundcolor>
            <height/>
            <width/>
            <hsizepolicy>Expanding</hsizepolicy>
            <vsizepolicy>Expanding</vsizepolicy>
            <frameshape>StyledPanel</frameshape>
            <frameshadow>Sunken</frameshadow>
            <showgrid>true</showgrid>
            <rowheight>40</rowheight>
            <bold>true</bold>
            <usepartialsums>true</usepartialsums>
            <selectionmode>SingleRow</selectionmode>
            <showhorheader>true</showhorheader>
            <showverheader>false</showverheader>
            <hscroll>off</hscroll>
            <vscroll>off</vscroll>
        </global>
        <columns>
            <column>
                <name>units</name>
                <text>Qty.</text>
                <description>Units</description>
                <show>true</show>
                <position>0</position>
                <icon/>
                <width>32</width>
            </column>
            <column>
                <name>description</name>
                <text>Description</text>
                <description>Product Description</description>
                <show>true</show>
                <position>1</position>
                <icon/>
                <width>147</width>
            </column>
            <column>
                <name>priority</name>
                <text>Priority</text>
                <description>Order Priority</description>
                <show>false</show>
                <position>2</position>
                <icon/>
                <width/>
            </column>
            <column>
                <name>timestamp</name>
                <text>TS</text>
                <description>Order Timestamp</description>
                <show>false</show>
                <position>3</position>
                <icon/>
                <width/>
            </column>
            <column>
                <name>price</name>
                <text>Price</text>
                <description>Product Price</description>
                <show>true</show>
                <position>4</position>
                <icon/>
                <width>45</width>
            </column>
        </columns>
    </tabledescription>
    <totaldescription>
        <global>
            <backgroundcolor>#FFFFFF</backgroundcolor>
            <height>150</height>
            <width/>
            <hsizepolicy>Expanding</hsizepolicy>
            <vsizepolicy>Maximum</vsizepolicy>
            <margin>0</margin>
            <spacing>5</spacing>
            <frameshape>Box</frameshape>
            <frameshadow>Plain</frameshadow>
            <layout>HBox</layout>
        </global>
        <labels>
            <label>
                <name>total_text</name>
                <text>TOTAL</text>
                <backgroundcolor>#2A44CF</backgroundcolor>
                <halign>Left</halign>
                <valign>Center</valign>
                <hsizepolicy>Preferred</hsizepolicy>
                <vsizepolicy>Maximum</vsizepolicy>
                <fontfamily>SansSerif</fontfamily>
                <fontsize>20</fontsize>
                <bold>true</bold>
            </label>
            <label>
                <name>total_amount</name>
                <text>0</text>
                <backgroundcolor>#1199CF</backgroundcolor>
                <halign>Right</halign>
                <valign>Center</valign>
                <hsizepolicy>Expanding</hsizepolicy>
                <vsizepolicy>Maximum</vsizepolicy>
                <fontfamily>SansSerif</fontfamily>
                <fontsize>25</fontsize>
                <bold>true</bold>
            </label>
            <label>
                <name>currency_symbol</name>
                <text>€</text>
                <backgroundcolor>#B2C105</backgroundcolor>
                <halign>Right</halign>
                <valign>Center</valign>
                <hsizepolicy>Maximum</hsizepolicy>
                <vsizepolicy>Maximum</vsizepolicy>
                <fontfamily>Arial</fontfamily>
                <fontsize>25</fontsize>
                <bold>true</bold>
            </label>
        </labels>
    </totaldescription>
</AUTOMATICALLY_GENERATED_XML>
